[{"Disease":"UMLS:C0020538_hypertensive disease","Count of Disease Occurrence":3363.0},{"Disease":"UMLS:C0011847_diabetes","Count of Disease Occurrence":1421.0},{"Disease":"UMLS:C0011570_depression mental^UMLS:C0011581_depressive disorder","Count of Disease Occurrence":1337.0},{"Disease":"UMLS:C0010054_coronary arteriosclerosis^UMLS:C0010068_coronary heart disease","Count of Disease Occurrence":1284.0},{"Disease":"UMLS:C0032285_pneumonia","Count of Disease Occurrence":1029.0},{"Disease":"UMLS:C0018802_failure heart congestive","Count of Disease Occurrence":963.0},{"Disease":"UMLS:C0038454_accident\u00a0cerebrovascular","Count of Disease Occurrence":885.0},{"Disease":"UMLS:C0004096_asthma","Count of Disease Occurrence":835.0},{"Disease":"UMLS:C0027051_myocardial infarction","Count of Disease Occurrence":759.0},{"Disease":"UMLS:C0020443_hypercholesterolemia","Count of Disease Occurrence":685.0},{"Disease":"UMLS:C0021311_infection","Count of Disease Occurrence":630.0},{"Disease":"UMLS:C0042029_infection urinary tract","Count of Disease Occurrence":597.0},{"Disease":"UMLS:C0002871_anemia","Count of Disease Occurrence":544.0},{"Disease":"UMLS:C0024117_chronic obstructive airway disease","Count of Disease Occurrence":524.0},{"Disease":"UMLS:C0497327_dementia","Count of Disease Occurrence":504.0},{"Disease":"UMLS:C1565489_insufficiency renal","Count of Disease Occurrence":445.0},{"Disease":"UMLS:C0009676_confusion","Count of Disease Occurrence":408.0},{"Disease":"UMLS:C0029408_degenerative\u00a0polyarthritis","Count of Disease Occurrence":405.0},{"Disease":"UMLS:C0020676_hypothyroidism","Count of Disease Occurrence":398.0},{"Disease":"UMLS:C0700613_anxiety state","Count of Disease Occurrence":390.0},{"Disease":"UMLS:C0006826_malignant neoplasms^UMLS:C1306459_primary malignant neoplasm","Count of Disease Occurrence":354.0},{"Disease":"UMLS:C0001175_acquired\u00a0immuno-deficiency syndrome^UMLS:C0019682_HIV^UMLS:C0019693_hiv infections","Count of Disease Occurrence":350.0},{"Disease":"UMLS:C0007642_cellulitis","Count of Disease Occurrence":341.0},{"Disease":"UMLS:C0017168_gastroesophageal reflux disease","Count of Disease Occurrence":325.0},{"Disease":"UMLS:C0036690_septicemia^UMLS:C0243026_systemic infection^UMLS:C1090821_sepsis (invertebrate)","Count of Disease Occurrence":311.0},{"Disease":"UMLS:C0149871_deep vein thrombosis","Count of Disease Occurrence":310.0},{"Disease":"UMLS:C0011175_dehydration","Count of Disease Occurrence":297.0},{"Disease":"UMLS:C0027651_neoplasm","Count of Disease Occurrence":297.0},{"Disease":"UMLS:C0034065_embolism pulmonary","Count of Disease Occurrence":294.0},{"Disease":"UMLS:C0014544_epilepsy","Count of Disease Occurrence":290.0},{"Disease":"UMLS:C0878544_cardiomyopathy","Count of Disease Occurrence":283.0},{"Disease":"UMLS:C0022661_chronic kidney failure","Count of Disease Occurrence":280.0},{"Disease":"UMLS:C0007097_carcinoma","Count of Disease Occurrence":269.0},{"Disease":"UMLS:C0019196_hepatitis C","Count of Disease Occurrence":269.0},{"Disease":"UMLS:C0085096_peripheral vascular disease","Count of Disease Occurrence":268.0},{"Disease":"UMLS:C0033975_psychotic disorder","Count of Disease Occurrence":267.0},{"Disease":"UMLS:C0020473_hyperlipidemia","Count of Disease Occurrence":247.0},{"Disease":"UMLS:C0005586_bipolar disorder","Count of Disease Occurrence":241.0},{"Disease":"UMLS:C0028754_obesity","Count of Disease Occurrence":228.0},{"Disease":"UMLS:C0022116_ischemia","Count of Disease Occurrence":226.0},{"Disease":"UMLS:C1623038_cirrhosis","Count of Disease Occurrence":218.0},{"Disease":"UMLS:C0015230_exanthema","Count of Disease Occurrence":208.0},{"Disease":"UMLS:C0005001_benign prostatic hypertrophy","Count of Disease Occurrence":192.0},{"Disease":"UMLS:C0022660_kidney failure acute","Count of Disease Occurrence":186.0},{"Disease":"UMLS:C0026266_mitral valve insufficiency","Count of Disease Occurrence":186.0},{"Disease":"UMLS:C0003864_arthritis","Count of Disease Occurrence":179.0},{"Disease":"UMLS:C0006277_bronchitis","Count of Disease Occurrence":172.0},{"Disease":"UMLS:C0018989_hemiparesis","Count of Disease Occurrence":171.0},{"Disease":"UMLS:C0029456_osteoporosis","Count of Disease Occurrence":169.0},{"Disease":"UMLS:C0007787_transient ischemic attack","Count of Disease Occurrence":168.0},{"Disease":"UMLS:C0001418_adenocarcinoma","Count of Disease Occurrence":166.0},{"Disease":"UMLS:C1456784_paranoia","Count of Disease Occurrence":165.0},{"Disease":"UMLS:C0030305_pancreatitis","Count of Disease Occurrence":165.0},{"Disease":"UMLS:C0021167_incontinence","Count of Disease Occurrence":165.0},{"Disease":"UMLS:C0013405_paroxysmal\u00a0dyspnea","Count of Disease Occurrence":165.0},{"Disease":"UMLS:C0019270_hernia","Count of Disease Occurrence":164.0},{"Disease":"UMLS:C0376358_malignant neoplasm of prostate^UMLS:C0600139_carcinoma prostate","Count of Disease Occurrence":163.0},{"Disease":"UMLS:C0034063_edema pulmonary","Count of Disease Occurrence":161.0},{"Disease":"UMLS:C0024228_lymphatic diseases","Count of Disease Occurrence":160.0},{"Disease":"UMLS:C0003507_stenosis aortic valve","Count of Disease Occurrence":158.0},{"Disease":"UMLS:C0006142_malignant neoplasm of breast^UMLS:C0678222_carcinoma breast","Count of Disease Occurrence":152.0},{"Disease":"UMLS:C0036341_schizophrenia","Count of Disease Occurrence":147.0},{"Disease":"UMLS:C0012813_diverticulitis","Count of Disease Occurrence":145.0},{"Disease":"UMLS:C0546817_overload fluid","Count of Disease Occurrence":144.0},{"Disease":"UMLS:C0030920_ulcer peptic","Count of Disease Occurrence":143.0},{"Disease":"UMLS:C0029443_osteomyelitis","Count of Disease Occurrence":142.0},{"Disease":"UMLS:C0017152_gastritis","Count of Disease Occurrence":140.0},{"Disease":"UMLS:C0004610_bacteremia","Count of Disease Occurrence":142.0},{"Disease":"UMLS:C0035078_failure kidney","Count of Disease Occurrence":140.0},{"Disease":"UMLS:C0002895_sickle cell anemia","Count of Disease Occurrence":140.0},{"Disease":"UMLS:C0018801_failure heart","Count of Disease Occurrence":138.0},{"Disease":"UMLS:C0041912_upper respiratory infection","Count of Disease Occurrence":135.0},{"Disease":"UMLS:C0019158_hepatitis","Count of Disease Occurrence":133.0},{"Disease":"UMLS:C0020542_hypertension pulmonary","Count of Disease Occurrence":128.0},{"Disease":"UMLS:C0011168_deglutition disorder","Count of Disease Occurrence":126.0},{"Disease":"UMLS:C0018099_gout","Count of Disease Occurrence":124.0},{"Disease":"UMLS:C0040034_thrombocytopaenia","Count of Disease Occurrence":123.0},{"Disease":"UMLS:C0020615_hypoglycemia","Count of Disease Occurrence":122.0},{"Disease":"UMLS:C0032290_pneumonia aspiration","Count of Disease Occurrence":119.0},{"Disease":"UMLS:C0009319_colitis","Count of Disease Occurrence":114.0},{"Disease":"UMLS:C1510475_diverticulosis","Count of Disease Occurrence":114.0},{"Disease":"UMLS:C0038663_suicide attempt","Count of Disease Occurrence":114.0},{"Disease":"UMLS:C0032305_Pneumocystis\u00a0carinii\u00a0pneumonia","Count of Disease Occurrence":113.0},{"Disease":"UMLS:C0019163_hepatitis B","Count of Disease Occurrence":111.0},{"Disease":"UMLS:C0030567_parkinson disease","Count of Disease Occurrence":108.0},{"Disease":"UMLS:C0024299_lymphoma","Count of Disease Occurrence":105.0},{"Disease":"UMLS:C0020456_hyperglycemia","Count of Disease Occurrence":104.0},{"Disease":"UMLS:C0085584_encephalopathy","Count of Disease Occurrence":103.0},{"Disease":"UMLS:C0040961_tricuspid valve insufficiency","Count of Disease Occurrence":101.0},{"Disease":"UMLS:C0002395_Alzheimer's disease","Count of Disease Occurrence":101.0},{"Disease":"UMLS:C0006840_candidiasis^UMLS:C0006849_oral\u00a0candidiasis","Count of Disease Occurrence":99.0},{"Disease":"UMLS:C0442874_neuropathy","Count of Disease Occurrence":99.0},{"Disease":"UMLS:C0022658_kidney disease","Count of Disease Occurrence":96.0},{"Disease":"UMLS:C0023267_fibroid tumor","Count of Disease Occurrence":96.0},{"Disease":"UMLS:C0017601_glaucoma","Count of Disease Occurrence":95.0},{"Disease":"UMLS:C0027627_neoplasm metastasis","Count of Disease Occurrence":94.0},{"Disease":"UMLS:C0007102_malignant tumor of colon^UMLS:C0699790_carcinoma colon","Count of Disease Occurrence":94.0},{"Disease":"UMLS:C0011880_ketoacidosis diabetic","Count of Disease Occurrence":93.0},{"Disease":"UMLS:C0014549_tonic-clonic epilepsy^UMLS:C0494475_tonic-clonic seizures","Count of Disease Occurrence":92.0},{"Disease":"UMLS:C0006826_malignant\u00a0neoplasms","Count of Disease Occurrence":90.0},{"Disease":"UMLS:C1145670_respiratory failure","Count of Disease Occurrence":90.0},{"Disease":"UMLS:C0025202_melanoma","Count of Disease Occurrence":87.0},{"Disease":"UMLS:C0017160_gastroenteritis","Count of Disease Occurrence":87.0},{"Disease":"UMLS:C0242379_malignant neoplasm of lung^UMLS:C0684249_carcinoma of lung","Count of Disease Occurrence":86.0},{"Disease":"UMLS:C0024713_manic disorder","Count of Disease Occurrence":85.0},{"Disease":"UMLS:C0031212_personality disorder","Count of Disease Occurrence":84.0},{"Disease":"UMLS:C0019204_primary carcinoma of the liver cells","Count of Disease Occurrence":82.0},{"Disease":"UMLS:C0034067_emphysema pulmonary","Count of Disease Occurrence":80.0},{"Disease":"UMLS:C0019112_hemorrhoids","Count of Disease Occurrence":80.0},{"Disease":"UMLS:C0006266_spasm bronchial","Count of Disease Occurrence":76.0},{"Disease":"UMLS:C0003537_aphasia","Count of Disease Occurrence":76.0},{"Disease":"UMLS:C0028756_obesity morbid","Count of Disease Occurrence":76.0},{"Disease":"UMLS:C0034186_pyelonephritis","Count of Disease Occurrence":74.0},{"Disease":"UMLS:C0014118_endocarditis","Count of Disease Occurrence":71.0},{"Disease":"UMLS:C0031039_effusion pericardial^UMLS:C1253937_pericardial effusion body substance","Count of Disease Occurrence":71.0},{"Disease":"UMLS:C0001973_chronic alcoholic intoxication","Count of Disease Occurrence":70.0},{"Disease":"UMLS:C0032326_pneumothorax","Count of Disease Occurrence":68.0},{"Disease":"UMLS:C0011206_delirium","Count of Disease Occurrence":68.0},{"Disease":"UMLS:C0027947_neutropenia","Count of Disease Occurrence":68.0},{"Disease":"UMLS:C0020433_hyperbilirubinemia","Count of Disease Occurrence":68.0},{"Disease":"UMLS:C0021400_influenza","Count of Disease Occurrence":68.0},{"Disease":"UMLS:C0439857_dependence","Count of Disease Occurrence":67.0},{"Disease":"UMLS:C0087086_thrombus","Count of Disease Occurrence":67.0},{"Disease":"UMLS:C0008325_cholecystitis","Count of Disease Occurrence":66.0},{"Disease":"UMLS:C0019291_hernia\u00a0hiatal","Count of Disease Occurrence":61.0},{"Disease":"UMLS:C0149931_migraine disorders","Count of Disease Occurrence":61.0},{"Disease":"UMLS:C0030312_pancytopenia","Count of Disease Occurrence":61.0},{"Disease":"UMLS:C0008350_cholelithiasis^UMLS:C0242216_biliary calculus","Count of Disease Occurrence":61.0},{"Disease":"UMLS:C0039239_tachycardia sinus","Count of Disease Occurrence":56.0},{"Disease":"UMLS:C1258215_ileus","Count of Disease Occurrence":56.0},{"Disease":"UMLS:C0001511_adhesion","Count of Disease Occurrence":57.0},{"Disease":"UMLS:C0011253_delusion","Count of Disease Occurrence":56.0},{"Disease":"UMLS:C0233472_affect labile","Count of Disease Occurrence":45.0},{"Disease":"UMLS:C0011127_decubitus ulcer","Count of Disease Occurrence":42.0}]